[{"USERJID":"559181857018@s.whatsapp.net"},{"USERJID":"5511914809389@s.whatsapp.net"},{"USERJID":"553799440244@s.whatsapp.net"},{"USERJID":"262692858888@s.whatsapp.net"},{"USERJID":"557399434240@s.whatsapp.net"},{"USERJID":"5511940099029@s.whatsapp.net"},{"USERJID":"4917383688887@s.whatsapp.net"},{"USERJID":"491745166956@s.whatsapp.net"},{"USERJID":"50052223@s.whatsapp.net"},{"USERJID":"5977585555@s.whatsapp.net"},{"USERJID":"66818888111@s.whatsapp.net"},{"USERJID":"4916355559555@s.whatsapp.net"},{"USERJID":"3167777775@s.whatsapp.net"}]